mp/__init__.py
mp/conbase.py
mp/conserial.py
mp/contelnet.py
mp/conwebsock.py
mp/mpfexp.py
mp/mpfshell.py
mp/pyboard.py
mp/retry.py
mp/term.py
mp/tokenizer.py
mp/version.py
mpfshell-0.9.3.dist-info/LICENSE
mpfshell-0.9.3.dist-info/METADATA
mpfshell-0.9.3.dist-info/WHEEL
mpfshell-0.9.3.dist-info/entry_points.txt
mpfshell-0.9.3.dist-info/top_level.txt
mpfshell-0.9.3.dist-info/RECORD
