Metadata-Version: 2.1
Name: mpfshell
Version: 0.9.3
Summary: A simple shell based file explorer for ESP8266 and WiPy Micropython devices.
Home-page: https://github.com/wendlers/mpfshell
Author: Stefan Wendler
Author-email: sw@kaltpost.de
License: UNKNOWN
Keywords: micropython,shell,file transfer,development
Platform: UNKNOWN
Requires-Dist: colorama
Requires-Dist: pyserial
Requires-Dist: websocket-client
